odoo/addons/base_duplicate_security_group/README.rst
odoo/addons/base_duplicate_security_group/__init__.py
odoo/addons/base_duplicate_security_group/__manifest__.py
odoo/addons/base_duplicate_security_group/i18n/base_duplicate_security_group.pot
odoo/addons/base_duplicate_security_group/readme/CONFIGURE.rst
odoo/addons/base_duplicate_security_group/readme/CONTRIBUTORS.rst
odoo/addons/base_duplicate_security_group/readme/DESCRIPTION.rst
odoo/addons/base_duplicate_security_group/security/base_duplicate_security_group_security.xml
odoo/addons/base_duplicate_security_group/static/description/icon.png
odoo/addons/base_duplicate_security_group/static/description/index.html
odoo/addons/base_duplicate_security_group/static/src/js/duplicate.js
odoo/addons/base_duplicate_security_group/static/src/js/tour_duplicate.js
odoo/addons/base_duplicate_security_group/tests/__init__.py
odoo/addons/base_duplicate_security_group/tests/test_base_duplicate_security_group.py
odoo/addons/base_duplicate_security_group/views/assets.xml
odoo13_addon_base_duplicate_security_group-13.0.1.0.1.dev3.dist-info/METADATA
odoo13_addon_base_duplicate_security_group-13.0.1.0.1.dev3.dist-info/WHEEL
odoo13_addon_base_duplicate_security_group-13.0.1.0.1.dev3.dist-info/top_level.txt
odoo13_addon_base_duplicate_security_group-13.0.1.0.1.dev3.dist-info/RECORD
